{
  "anchor_type": "manual_external_post",
  "external_ref": "https://github.com/m-sirius-k/MoCKA/commit/6ce31bc817fee2d116fa68f9ee0b5c4349dd75f9",
  "external_ref_semantics": "sealing_commit_reference",
  "schema": "mocka.governance.anchor_record.v1",
  "note": "Re-anchored after security cleanup 2026-04-16 E20260416_002",
  "sealed_summary_hash": "1e63bd3bc745d27290251777609ab2bb52328ba670da2b44aa33889d18938deb",
  "sealed_at_utc": "2026-06-11T07:04:27Z",
  "summary_hash_spec_version": "1.0"
}