{
  "anchor_type": "manual_external_post",
  "external_ref": "https://github.com/m-sirius-k/MoCKA/commit/1b247a951e19653aea047f0e317ca6f1e06f1093",
  "external_ref_semantics": "sealing_commit_reference",
  "schema": "mocka.governance.anchor_record.v1",
  "note": "Re-anchored after security cleanup 2026-04-16 E20260416_002",
  "sealed_summary_hash": "b8d607c2a0c3a752775f561831754f26c965307ebaa0fe9174f077d9e4149e7d",
  "sealed_at_utc": "2026-05-30T06:06:51Z",
  "summary_hash_spec_version": "1.0"
}