{
  "anchor_type": "manual_external_post",
  "external_ref": "https://github.com/m-sirius-k/MoCKA/commit/eaf23ceb88b4848ffb59c9b0d185e81b4fa73db5",
  "external_ref_semantics": "sealing_commit_reference",
  "schema": "mocka.governance.anchor_record.v1",
  "note": "Re-anchored after security cleanup 2026-04-16 E20260416_002",
  "sealed_summary_hash": "3fa5da6615b1e6ab89fc212b23590b9be9652060170c9b5c7e69cfe53faf4898",
  "sealed_at_utc": "2026-05-22T04:27:36Z",
  "summary_hash_spec_version": "1.0"
}