{
  "anchor_type": "manual_external_post",
  "external_ref": "https://github.com/m-sirius-k/MoCKA/commit/780aed39979f51c759c74592c6b1d04793d21a93",
  "external_ref_semantics": "sealing_commit_reference",
  "schema": "mocka.governance.anchor_record.v1",
  "note": "Re-anchored after security cleanup 2026-04-16 E20260416_002",
  "sealed_summary_hash": "3242665b106d43914a054bc7883fc74d615beda3c291f4da3b1702a6ea4d77ed",
  "sealed_at_utc": "2026-06-10T09:51:54Z",
  "summary_hash_spec_version": "1.0"
}