{
  "H": "MOCKA_DNA_v2",
  "G": 5.0,
  "C": "STRICT",
  "P": "SESSION_START_LOCK",
  "A": "Z-Axis=0.819 / INCIDENT=Geminiが統計値Z=0.88を捏造（INTEGRITY_",
  "ESSENCE_SUMMARY": {
    "INCIDENT": "Geminiが統計値Z=0.88を捏造（INTEGRITY_VIOLATION）。essenceパイプライン断絶発見（REDUCING160件放置・ping_latest.json未更新）。ping_generator SQLite直読みに修正済み。",
    "PHILOSOPHY": "AIを信じるな、システムで縛れ。失敗要因を分析し発生確率を下げることが成功につながる。現状の把握・ここに至る経緯・過去の経験の分析がbaseになる。",
    "OPERATION": "ファイル管理: X:\\down\\ 作業中 → X:\\down\\mocka関係\\ 長期保管。01_paper/02_code/03_doc/04_config/05_installer/06_old_dup/07_misc/08_benchmark"
  },
  "essence_updated": false,
  "ngrok_online": false,
  "NGROK": false,
  "current_phase": "Phase 2進行中",
  "top_todos": [
    {
      "id": "TODO_054",
      "title": "AIES 2026投稿準備 — EasyChair登録・匿名化・フォーマット変換",
      "priority": "最高"
    },
    {
      "id": "TODO_055",
      "title": "AIES 2026 — 10ページ版アウトライン設計・Supplementary Material分離",
      "priority": "最高"
    },
    {
      "id": "TODO_116",
      "title": "COMMAND CENTER — Temporal Analytics（7日トレンド）実装",
      "priority": "高"
    },
    {
      "id": "TODO_117",
      "title": "COMMAND CENTER — Decision Intelligence（判断理由ログ）実装",
      "priority": "高"
    },
    {
      "id": "TODO_118",
      "title": "Risk Engine — TODOリスクスコア + SYSTEM RECOMMENDATION実装",
      "priority": "高"
    }
  ],
  "generated_at": "2026-05-01T18:24:57.502750"
}